mermaidmro/__init__.py
mermaidmro/__meta__.py
mermaidmro-0.2.1.dist-info/LICENSE
mermaidmro-0.2.1.dist-info/METADATA
mermaidmro-0.2.1.dist-info/WHEEL
mermaidmro-0.2.1.dist-info/entry_points.txt
mermaidmro-0.2.1.dist-info/top_level.txt
mermaidmro-0.2.1.dist-info/RECORD
