Metadata-Version: 2.1
Name: mermaidmro
Version: 0.2.1
Summary: Create mermaid graphs from the method resolution order (mro) of Python objects.
Author-email: Marcel Rieger <github.riga@icloud.com>
License: Copyright (c) 2023, Marcel Rieger
Project-URL: Homepage, https://github.com/riga/mermaidmro
Project-URL: Documentation, https://mermaidmro.readthedocs.io
Project-URL: Repository, https://github.com/riga/mermaidmro.git
Keywords: mro,graph,inheritance,mermaid,dag
Classifier: Programming Language :: Python
Classifier: Programming Language :: Python :: 3
Classifier: Programming Language :: Python :: 3.7
Classifier: Programming Language :: Python :: 3.8
Classifier: Programming Language :: Python :: 3.9
Classifier: Programming Language :: Python :: 3.10
Classifier: Programming Language :: Python :: 3.11
Classifier: Programming Language :: Python :: 3.12
Classifier: Operating System :: OS Independent
Classifier: License :: OSI Approved :: BSD License
Classifier: Intended Audience :: Developers
Classifier: Intended Audience :: Science/Research
Classifier: Intended Audience :: Information Technology
Requires-Python: >=3.7
License-File: LICENSE
Provides-Extra: dev
Requires-Dist: requests ~=2.28.1 ; extra == 'dev'
Requires-Dist: flake8 ~=5.0 ; extra == 'dev'
Requires-Dist: flake8-commas ~=2.1 ; extra == 'dev'
Requires-Dist: flake8-quotes ~=3.3 ; extra == 'dev'
Requires-Dist: pytest ~=7.4.0 ; extra == 'dev'
Requires-Dist: pytest-cov ~=4.1.0 ; extra == 'dev'
